{
"meta":{"test_sets":[],"test_metrics":[],"learn_metrics":[{"best_value":"Min","name":"Logloss"}],"launch_mode":"Train","parameters":"","iteration_count":622,"learn_sets":["learn"],"name":"experiment"},
"iterations":[
{"learn":[0.6567277022],"iteration":0,"passed_time":0.03706963199,"remaining_time":23.02024146},
{"learn":[0.6300894791],"iteration":1,"passed_time":0.05690895194,"remaining_time":17.6417751},
{"learn":[0.6076288672],"iteration":2,"passed_time":0.07746131641,"remaining_time":15.98285162},
{"learn":[0.5855256681],"iteration":3,"passed_time":0.09957148484,"remaining_time":15.38379441},
{"learn":[0.5675956867],"iteration":4,"passed_time":0.1196435166,"remaining_time":14.76400995},
{"learn":[0.5523041053],"iteration":5,"passed_time":0.1410296914,"remaining_time":14.47904832},
{"learn":[0.5387001066],"iteration":6,"passed_time":0.1674984519,"remaining_time":14.71593542},
{"learn":[0.5297807034],"iteration":7,"passed_time":0.1882637788,"remaining_time":14.44924503},
{"learn":[0.5220849316],"iteration":8,"passed_time":0.2114915301,"remaining_time":14.40492311},
{"learn":[0.5144362483],"iteration":9,"passed_time":0.2335457707,"remaining_time":14.29300116},
{"learn":[0.5086858949],"iteration":10,"passed_time":0.2532747091,"remaining_time":14.06825884},
{"learn":[0.5027206097],"iteration":11,"passed_time":0.2748155715,"remaining_time":13.96979155},
{"learn":[0.4974711713],"iteration":12,"passed_time":0.2971175675,"remaining_time":13.91881528},
{"learn":[0.4934560771],"iteration":13,"passed_time":0.3221754565,"remaining_time":13.99161983},
{"learn":[0.4901934558],"iteration":14,"passed_time":0.3450476441,"remaining_time":13.962928},
{"learn":[0.4873907729],"iteration":15,"passed_time":0.3673781774,"remaining_time":13.91444847},
{"learn":[0.4849592698],"iteration":16,"passed_time":0.3903115313,"remaining_time":13.89049861},
{"learn":[0.481900952],"iteration":17,"passed_time":0.4140466077,"remaining_time":13.89356395},
{"learn":[0.4796890733],"iteration":18,"passed_time":0.4366810602,"remaining_time":13.85887786},
{"learn":[0.4779088503],"iteration":19,"passed_time":0.4602799578,"remaining_time":13.85442673},
{"learn":[0.475974996],"iteration":20,"passed_time":0.4839886278,"remaining_time":13.85129358},
{"learn":[0.4746111684],"iteration":21,"passed_time":0.5063070688,"remaining_time":13.8083746},
{"learn":[0.473101948],"iteration":22,"passed_time":0.5298978085,"remaining_time":13.80038206},
{"learn":[0.4719601647],"iteration":23,"passed_time":0.5529942446,"remaining_time":13.77877326},
{"learn":[0.4709737848],"iteration":24,"passed_time":0.5774062024,"remaining_time":13.78846011},
{"learn":[0.4701641247],"iteration":25,"passed_time":0.5985078915,"remaining_time":13.71964244},
{"learn":[0.4694596081],"iteration":26,"passed_time":0.6200036024,"remaining_time":13.66304235},
{"learn":[0.4685558029],"iteration":27,"passed_time":0.6422922275,"remaining_time":13.62577083},
{"learn":[0.467357375],"iteration":28,"passed_time":0.6665447663,"remaining_time":13.62969126},
{"learn":[0.4668273583],"iteration":29,"passed_time":0.6869123624,"remaining_time":13.55507062},
{"learn":[0.46633556],"iteration":30,"passed_time":0.7097915313,"remaining_time":13.5318321},
{"learn":[0.4658535393],"iteration":31,"passed_time":0.7310291036,"remaining_time":13.4783491},
{"learn":[0.4649003011],"iteration":32,"passed_time":0.754457835,"remaining_time":13.46592924},
{"learn":[0.4640849601],"iteration":33,"passed_time":0.780584498,"remaining_time":13.49952014},
{"learn":[0.4636256954],"iteration":34,"passed_time":0.8038506415,"remaining_time":13.48172362},
{"learn":[0.4630971758],"iteration":35,"passed_time":0.8278462834,"remaining_time":13.47549783},
{"learn":[0.4626381181],"iteration":36,"passed_time":0.8498306665,"remaining_time":13.43651189},
{"learn":[0.4621633046],"iteration":37,"passed_time":0.8735064726,"remaining_time":13.42441526},
{"learn":[0.4619310828],"iteration":38,"passed_time":0.8934923345,"remaining_time":13.3565649},
{"learn":[0.4615808869],"iteration":39,"passed_time":0.9179576777,"remaining_time":13.35628421},
{"learn":[0.461335626],"iteration":40,"passed_time":0.9363324979,"remaining_time":13.26851662},
{"learn":[0.4610256829],"iteration":41,"passed_time":0.9573205101,"remaining_time":13.22014038},
{"learn":[0.4608037908],"iteration":42,"passed_time":0.9789766289,"remaining_time":13.18203414},
{"learn":[0.4604290518],"iteration":43,"passed_time":1.002355576,"remaining_time":13.16730734},
{"learn":[0.4601428707],"iteration":44,"passed_time":1.028132452,"remaining_time":13.18294277},
{"learn":[0.4598445255],"iteration":45,"passed_time":1.048883532,"remaining_time":13.13384596},
{"learn":[0.459608128],"iteration":46,"passed_time":1.072822477,"remaining_time":13.12495584},
{"learn":[0.4592726608],"iteration":47,"passed_time":1.09445452,"remaining_time":13.08785197},
{"learn":[0.459102616],"iteration":48,"passed_time":1.116759415,"remaining_time":13.05924785},
{"learn":[0.4588289456],"iteration":49,"passed_time":1.139966996,"remaining_time":13.04122243},
{"learn":[0.4586046273],"iteration":50,"passed_time":1.163221533,"remaining_time":13.02351952},
{"learn":[0.4583302864],"iteration":51,"passed_time":1.185319757,"remaining_time":12.9929281},
{"learn":[0.4580080528],"iteration":52,"passed_time":1.208171024,"remaining_time":12.97074175},
{"learn":[0.4578277903],"iteration":53,"passed_time":1.233582996,"remaining_time":12.97546559},
{"learn":[0.4575201266],"iteration":54,"passed_time":1.253568101,"remaining_time":12.92314752},
{"learn":[0.4573051705],"iteration":55,"passed_time":1.27462195,"remaining_time":12.88278614},
{"learn":[0.4571161611],"iteration":56,"passed_time":1.296839667,"remaining_time":12.8546388},
{"learn":[0.4569650017],"iteration":57,"passed_time":1.31956693,"remaining_time":12.83165084},
{"learn":[0.456769271],"iteration":58,"passed_time":1.339928886,"remaining_time":12.78610106},
{"learn":[0.4566167786],"iteration":59,"passed_time":1.362164361,"remaining_time":12.75893951},
{"learn":[0.4564275252],"iteration":60,"passed_time":1.384220957,"remaining_time":12.73029438},
{"learn":[0.4562391671],"iteration":61,"passed_time":1.405427873,"remaining_time":12.69418724},
{"learn":[0.4560834564],"iteration":62,"passed_time":1.428919427,"remaining_time":12.67882476},
{"learn":[0.455952164],"iteration":63,"passed_time":1.451184746,"remaining_time":12.65251701},
{"learn":[0.4557836819],"iteration":64,"passed_time":1.471900014,"remaining_time":12.61305089},
{"learn":[0.4556424907],"iteration":65,"passed_time":1.493406755,"remaining_time":12.58082054},
{"learn":[0.4554817799],"iteration":66,"passed_time":1.514492282,"remaining_time":12.54542114},
{"learn":[0.4553082997],"iteration":67,"passed_time":1.537788061,"remaining_time":12.52844979},
{"learn":[0.4551503045],"iteration":68,"passed_time":1.557948553,"remaining_time":12.48616739},
{"learn":[0.4549073325],"iteration":69,"passed_time":1.581728469,"remaining_time":12.47305878},
{"learn":[0.4548124051],"iteration":70,"passed_time":1.602534053,"remaining_time":12.43656708},
{"learn":[0.4547052235],"iteration":71,"passed_time":1.621942417,"remaining_time":12.38983791},
{"learn":[0.4545880691],"iteration":72,"passed_time":1.644114071,"remaining_time":12.3646387},
{"learn":[0.4544801104],"iteration":73,"passed_time":1.666855241,"remaining_time":12.34373881},
{"learn":[0.4543938284],"iteration":74,"passed_time":1.688537368,"remaining_time":12.31506587},
{"learn":[0.4543238948],"iteration":75,"passed_time":1.710538261,"remaining_time":12.28886698},
{"learn":[0.4542593434],"iteration":76,"passed_time":1.731435356,"remaining_time":12.25496453},
{"learn":[0.4541426885],"iteration":77,"passed_time":1.752716856,"remaining_time":12.22407653},
{"learn":[0.4540260213],"iteration":78,"passed_time":1.776253545,"remaining_time":12.20893259},
{"learn":[0.4539073413],"iteration":79,"passed_time":1.796558959,"remaining_time":12.17168695},
{"learn":[0.4537589282],"iteration":80,"passed_time":1.819212685,"remaining_time":12.15054398},
{"learn":[0.4536872812],"iteration":81,"passed_time":1.839819436,"remaining_time":12.11588409},
{"learn":[0.4535786668],"iteration":82,"passed_time":1.860923718,"remaining_time":12.08479378},
{"learn":[0.4534608692],"iteration":83,"passed_time":1.884594817,"remaining_time":12.07038109},
{"learn":[0.4533566062],"iteration":84,"passed_time":1.904514437,"remaining_time":12.03205003},
{"learn":[0.4532963391],"iteration":85,"passed_time":1.926557586,"remaining_time":12.00738216},
{"learn":[0.4531175461],"iteration":86,"passed_time":1.951174324,"remaining_time":11.99860073},
{"learn":[0.4529809151],"iteration":87,"passed_time":1.973705152,"remaining_time":11.97680172},
{"learn":[0.452882039],"iteration":88,"passed_time":1.994792775,"remaining_time":11.94634325},
{"learn":[0.4527727553],"iteration":89,"passed_time":2.018879294,"remaining_time":11.93381983},
{"learn":[0.4526900063],"iteration":90,"passed_time":2.040573005,"remaining_time":11.90707984},
{"learn":[0.4525974761],"iteration":91,"passed_time":2.063221762,"remaining_time":11.88595146},
{"learn":[0.4525374434],"iteration":92,"passed_time":2.084115555,"remaining_time":11.85480783},
{"learn":[0.4524781842],"iteration":93,"passed_time":2.105190653,"remaining_time":11.82490069},
{"learn":[0.452379671],"iteration":94,"passed_time":2.12670728,"remaining_time":11.79762881},
{"learn":[0.4522973283],"iteration":95,"passed_time":2.15056986,"remaining_time":11.78333069},
{"learn":[0.4521945417],"iteration":96,"passed_time":2.171384067,"remaining_time":11.75233645},
{"learn":[0.4521269099],"iteration":97,"passed_time":2.191312933,"remaining_time":11.71681609},
{"learn":[0.4520378809],"iteration":98,"passed_time":2.213988003,"remaining_time":11.69611844},
{"learn":[0.4519753961],"iteration":99,"passed_time":2.23652706,"remaining_time":11.67467125},
{"learn":[0.4518972169],"iteration":100,"passed_time":2.257211337,"remaining_time":11.64363472},
{"learn":[0.4518071688],"iteration":101,"passed_time":2.276506631,"remaining_time":11.60572008},
{"learn":[0.4516956886],"iteration":102,"passed_time":2.300752635,"remaining_time":11.59311279},
{"learn":[0.4516730832],"iteration":103,"passed_time":2.319017293,"remaining_time":11.55048998},
{"learn":[0.451572221],"iteration":104,"passed_time":2.343115464,"remaining_time":11.53705424},
{"learn":[0.4515019303],"iteration":105,"passed_time":2.368121882,"remaining_time":11.52783859},
{"learn":[0.451460772],"iteration":106,"passed_time":2.388142638,"remaining_time":11.49433139},
{"learn":[0.4513871977],"iteration":107,"passed_time":2.411119281,"remaining_time":11.47514176},
{"learn":[0.4513495519],"iteration":108,"passed_time":2.431550491,"remaining_time":11.44390277},
{"learn":[0.4512620107],"iteration":109,"passed_time":2.454902136,"remaining_time":11.42645358},
{"learn":[0.451171057],"iteration":110,"passed_time":2.477226992,"remaining_time":11.40417111},
{"learn":[0.4511112824],"iteration":111,"passed_time":2.500409954,"remaining_time":11.38579533},
{"learn":[0.4510410993],"iteration":112,"passed_time":2.520205446,"remaining_time":11.35207586},
{"learn":[0.4509550986],"iteration":113,"passed_time":2.542585355,"remaining_time":11.33011719},
{"learn":[0.4508751872],"iteration":114,"passed_time":2.564294568,"remaining_time":11.30519431},
{"learn":[0.4507703049],"iteration":115,"passed_time":2.587760109,"remaining_time":11.28798806},
{"learn":[0.4507359326],"iteration":116,"passed_time":2.609649932,"remaining_time":11.26387364},
{"learn":[0.450674462],"iteration":117,"passed_time":2.631850847,"remaining_time":11.24112565},
{"learn":[0.4506213614],"iteration":118,"passed_time":2.654237107,"remaining_time":11.21917029},
{"learn":[0.4505515333],"iteration":119,"passed_time":2.673753544,"remaining_time":11.18520232},
{"learn":[0.4504718298],"iteration":120,"passed_time":2.699014694,"remaining_time":11.17525919},
{"learn":[0.4504142515],"iteration":121,"passed_time":2.719516682,"remaining_time":11.14556017},
{"learn":[0.4503645582],"iteration":122,"passed_time":2.746685713,"remaining_time":11.1430583},
{"learn":[0.4503352433],"iteration":123,"passed_time":2.765943494,"remaining_time":11.10838597},
{"learn":[0.4502559929],"iteration":124,"passed_time":2.788762837,"remaining_time":11.08812104},
{"learn":[0.4501914332],"iteration":125,"passed_time":2.811887324,"remaining_time":11.06901677},
{"learn":[0.450114303],"iteration":126,"passed_time":2.836851804,"remaining_time":11.05702081},
{"learn":[0.4500710108],"iteration":127,"passed_time":2.86005637,"remaining_time":11.03803005},
{"learn":[0.4500236319],"iteration":128,"passed_time":2.882223371,"remaining_time":11.0150087},
{"learn":[0.4499509197],"iteration":129,"passed_time":2.903881255,"remaining_time":10.99007367},
{"learn":[0.4498669436],"iteration":130,"passed_time":2.928452435,"remaining_time":10.97610798},
{"learn":[0.4497945079],"iteration":131,"passed_time":2.951425597,"remaining_time":10.95604957},
{"learn":[0.4497362303],"iteration":132,"passed_time":2.972982049,"remaining_time":10.93073851},
{"learn":[0.4496866503],"iteration":133,"passed_time":2.992864752,"remaining_time":10.89938805},
{"learn":[0.4496582542],"iteration":134,"passed_time":3.01562804,"remaining_time":10.87859893},
{"learn":[0.4495752701],"iteration":135,"passed_time":3.03623472,"remaining_time":10.85007407},
{"learn":[0.4495377686],"iteration":136,"passed_time":3.055993445,"remaining_time":10.81866293},
{"learn":[0.4494929265],"iteration":137,"passed_time":3.078721372,"remaining_time":10.79783438},
{"learn":[0.4494449151],"iteration":138,"passed_time":3.099521439,"remaining_time":10.77027953},
{"learn":[0.449393849],"iteration":139,"passed_time":3.123493878,"remaining_time":10.75374321},
{"learn":[0.4493506243],"iteration":140,"passed_time":3.143658564,"remaining_time":10.72411184},
{"learn":[0.4493107505],"iteration":141,"passed_time":3.16474872,"remaining_time":10.69774215},
{"learn":[0.4492275731],"iteration":142,"passed_time":3.186955926,"remaining_time":10.67518803},
{"learn":[0.4491531371],"iteration":143,"passed_time":3.210255678,"remaining_time":10.65626537},
{"learn":[0.4491032138],"iteration":144,"passed_time":3.232337503,"remaining_time":10.63327579},
{"learn":[0.4490377202],"iteration":145,"passed_time":3.254991018,"remaining_time":10.6121625},
{"learn":[0.4489967194],"iteration":146,"passed_time":3.276081343,"remaining_time":10.58597713},
{"learn":[0.4489498269],"iteration":147,"passed_time":3.298655766,"remaining_time":10.56461374},
{"learn":[0.4489288842],"iteration":148,"passed_time":3.318536114,"remaining_time":10.53468176},
{"learn":[0.4488917704],"iteration":149,"passed_time":3.34181279,"remaining_time":10.51557091},
{"learn":[0.4488712171],"iteration":150,"passed_time":3.361513823,"remaining_time":10.48525173},
{"learn":[0.4487871948],"iteration":151,"passed_time":3.384334875,"remaining_time":10.46471968},
{"learn":[0.4487545267],"iteration":152,"passed_time":3.403766817,"remaining_time":10.43376887},
{"learn":[0.448677305],"iteration":153,"passed_time":3.428026875,"remaining_time":10.41764011},
{"learn":[0.4485961795],"iteration":154,"passed_time":3.451772215,"remaining_time":10.39985564},
{"learn":[0.4485402533],"iteration":155,"passed_time":3.474368068,"remaining_time":10.37856102},
{"learn":[0.4485007654],"iteration":156,"passed_time":3.496926192,"remaining_time":10.35713808},
{"learn":[0.4484417822],"iteration":157,"passed_time":3.517009058,"remaining_time":10.32843166},
{"learn":[0.4483291064],"iteration":158,"passed_time":3.543210147,"remaining_time":10.31764967},
{"learn":[0.4482598117],"iteration":159,"passed_time":3.568492443,"remaining_time":10.30402193},
{"learn":[0.4481945539],"iteration":160,"passed_time":3.590178621,"remaining_time":10.27995245},
{"learn":[0.4481298753],"iteration":161,"passed_time":3.612443607,"remaining_time":10.25755592},
{"learn":[0.4481072313],"iteration":162,"passed_time":3.630582038,"remaining_time":10.22354083},
{"learn":[0.4480437205],"iteration":163,"passed_time":3.650915624,"remaining_time":10.19584973},
{"learn":[0.447993491],"iteration":164,"passed_time":3.675071077,"remaining_time":10.17883323},
{"learn":[0.447939097],"iteration":165,"passed_time":3.696954347,"remaining_time":10.15548905},
{"learn":[0.4478887966],"iteration":166,"passed_time":3.718463738,"remaining_time":10.13114372},
{"learn":[0.4478261652],"iteration":167,"passed_time":3.739926968,"remaining_time":10.1067074},
{"learn":[0.4477652838],"iteration":168,"passed_time":3.76395254,"remaining_time":10.08917456},
{"learn":[0.4476650016],"iteration":169,"passed_time":3.790339861,"remaining_time":10.07784481},
{"learn":[0.4476302703],"iteration":170,"passed_time":3.809736377,"remaining_time":10.0479012},
{"learn":[0.4475632773],"iteration":171,"passed_time":3.830252391,"remaining_time":10.02100916},
{"learn":[0.4475233986],"iteration":172,"passed_time":3.852077494,"remaining_time":9.99758841},
{"learn":[0.4474169294],"iteration":173,"passed_time":3.877828604,"remaining_time":9.984294337},
{"learn":[0.4473396784],"iteration":174,"passed_time":3.903353426,"remaining_time":9.970279895},
{"learn":[0.4472860635],"iteration":175,"passed_time":3.924809161,"remaining_time":9.945823216},
{"learn":[0.4472033599],"iteration":176,"passed_time":3.947201131,"remaining_time":9.923754257},
{"learn":[0.447144274],"iteration":177,"passed_time":3.968175898,"remaining_time":9.898146623},
{"learn":[0.4470908958],"iteration":178,"passed_time":3.9898955,"remaining_time":9.874434114},
{"learn":[0.4470018907],"iteration":179,"passed_time":4.012312412,"remaining_time":9.852456034},
{"learn":[0.4469171504],"iteration":180,"passed_time":4.034214374,"remaining_time":9.829218447},
{"learn":[0.4468537943],"iteration":181,"passed_time":4.057277854,"remaining_time":9.808803604},
{"learn":[0.4467594757],"iteration":182,"passed_time":4.081986831,"remaining_time":9.792307206},
{"learn":[0.4466693197],"iteration":183,"passed_time":4.107177577,"remaining_time":9.776868362},
{"learn":[0.446614822],"iteration":184,"passed_time":4.128624823,"remaining_time":9.75248134},
{"learn":[0.4465314812],"iteration":185,"passed_time":4.1522457,"remaining_time":9.733221104},
{"learn":[0.4464643366],"iteration":186,"passed_time":4.175529253,"remaining_time":9.713129546},
{"learn":[0.4463971231],"iteration":187,"passed_time":4.197483019,"remaining_time":9.689934204},
{"learn":[0.4463187325],"iteration":188,"passed_time":4.221881835,"remaining_time":9.672353623},
{"learn":[0.4462376471],"iteration":189,"passed_time":4.246863498,"remaining_time":9.656026481},
{"learn":[0.4461533159],"iteration":190,"passed_time":4.271941117,"remaining_time":9.639825243},
{"learn":[0.4460781661],"iteration":191,"passed_time":4.294121972,"remaining_time":9.617043999},
{"learn":[0.4460060077],"iteration":192,"passed_time":4.316113559,"remaining_time":9.593848274},
{"learn":[0.4459319054],"iteration":193,"passed_time":4.339254895,"remaining_time":9.573201521},
{"learn":[0.4458596935],"iteration":194,"passed_time":4.36111137,"remaining_time":9.549715666},
{"learn":[0.4457791663],"iteration":195,"passed_time":4.383434166,"remaining_time":9.527259972},
{"learn":[0.4457037151],"iteration":196,"passed_time":4.407368701,"remaining_time":9.508282731},
{"learn":[0.4456317613],"iteration":197,"passed_time":4.432343023,"remaining_time":9.49148203},
{"learn":[0.4455480834],"iteration":198,"passed_time":4.457252088,"remaining_time":9.474460468},
{"learn":[0.4454849163],"iteration":199,"passed_time":4.479377233,"remaining_time":9.451485962},
{"learn":[0.4453990187],"iteration":200,"passed_time":4.504526098,"remaining_time":9.434853171},
{"learn":[0.4453369474],"iteration":201,"passed_time":4.52635178,"remaining_time":9.411226473},
{"learn":[0.4452555237],"iteration":202,"passed_time":4.552883286,"remaining_time":9.397330526},
{"learn":[0.445200157],"iteration":203,"passed_time":4.574562808,"remaining_time":9.373368891},
{"learn":[0.4451299952],"iteration":204,"passed_time":4.600844498,"remaining_time":9.358791002},
{"learn":[0.4450517235],"iteration":205,"passed_time":4.624129933,"remaining_time":9.338048798},
{"learn":[0.4449840509],"iteration":206,"passed_time":4.650192073,"remaining_time":9.322848842},
{"learn":[0.4449148029],"iteration":207,"passed_time":4.672910028,"remaining_time":9.300888229},
{"learn":[0.4448624381],"iteration":208,"passed_time":4.693489754,"remaining_time":9.274695065},
{"learn":[0.4447936695],"iteration":209,"passed_time":4.716497241,"remaining_time":9.253318396},
{"learn":[0.444724357],"iteration":210,"passed_time":4.737735069,"remaining_time":9.228479211},
{"learn":[0.4446614117],"iteration":211,"passed_time":4.76064105,"remaining_time":9.206900143},
{"learn":[0.4445959959],"iteration":212,"passed_time":4.785982613,"remaining_time":9.189985394},
{"learn":[0.4445163737],"iteration":213,"passed_time":4.808852373,"remaining_time":9.168279291},
{"learn":[0.4444525202],"iteration":214,"passed_time":4.829902531,"remaining_time":9.143117814},
{"learn":[0.4443899193],"iteration":215,"passed_time":4.851986933,"remaining_time":9.119938402},
{"learn":[0.4443288007],"iteration":216,"passed_time":4.875230207,"remaining_time":9.098931953},
{"learn":[0.4442566029],"iteration":217,"passed_time":4.901179572,"remaining_time":9.082919941},
{"learn":[0.4441893494],"iteration":218,"passed_time":4.925017438,"remaining_time":9.062931632},
{"learn":[0.4441437506],"iteration":219,"passed_time":4.945694743,"remaining_time":9.037133121},
{"learn":[0.4440777856],"iteration":220,"passed_time":4.970774918,"remaining_time":9.019369874},
{"learn":[0.444007429],"iteration":221,"passed_time":4.997504271,"remaining_time":9.004512201},
{"learn":[0.4439455227],"iteration":222,"passed_time":5.019591482,"remaining_time":8.981242159},
{"learn":[0.4438839563],"iteration":223,"passed_time":5.041696119,"remaining_time":8.95801364},
{"learn":[0.4438300568],"iteration":224,"passed_time":5.063172715,"remaining_time":8.933686968},
{"learn":[0.4437626017],"iteration":225,"passed_time":5.087241067,"remaining_time":8.913926826},
{"learn":[0.4437140577],"iteration":226,"passed_time":5.107706245,"remaining_time":8.887858885},
{"learn":[0.4436443707],"iteration":227,"passed_time":5.132178526,"remaining_time":8.868764646},
{"learn":[0.4435722413],"iteration":228,"passed_time":5.154330349,"remaining_time":8.845641166},
{"learn":[0.4435115698],"iteration":229,"passed_time":5.179842523,"remaining_time":8.828253344},
{"learn":[0.4434288776],"iteration":230,"passed_time":5.207289061,"remaining_time":8.814069363},
{"learn":[0.4433713121],"iteration":231,"passed_time":5.23049127,"remaining_time":8.792636187},
{"learn":[0.4433077612],"iteration":232,"passed_time":5.254470299,"remaining_time":8.772484747},
{"learn":[0.4432388984],"iteration":233,"passed_time":5.278491681,"remaining_time":8.752370821},
{"learn":[0.4431868282],"iteration":234,"passed_time":5.299890866,"remaining_time":8.727905384},
{"learn":[0.443132302],"iteration":235,"passed_time":5.324510015,"remaining_time":8.708732482},
{"learn":[0.4430612359],"iteration":236,"passed_time":5.350458184,"remaining_time":8.691672577},
{"learn":[0.4430147375],"iteration":237,"passed_time":5.371864242,"remaining_time":8.667209534},
{"learn":[0.4429648699],"iteration":238,"passed_time":5.39363422,"remaining_time":8.643355257},
{"learn":[0.4428990571],"iteration":239,"passed_time":5.418747644,"remaining_time":8.624839999},
{"learn":[0.4428368498],"iteration":240,"passed_time":5.444307431,"remaining_time":8.606975649},
{"learn":[0.4427695355],"iteration":241,"passed_time":5.489466247,"remaining_time":8.619823032},
{"learn":[0.4427185417],"iteration":242,"passed_time":5.517375888,"remaining_time":8.605289965},
{"learn":[0.4426695457],"iteration":243,"passed_time":5.539409826,"remaining_time":8.58154473},
{"learn":[0.4426128577],"iteration":244,"passed_time":5.563466688,"remaining_time":8.560926292},
{"learn":[0.4425526509],"iteration":245,"passed_time":5.585359875,"remaining_time":8.536972817},
{"learn":[0.4424862863],"iteration":246,"passed_time":5.609601753,"remaining_time":8.516601852},
{"learn":[0.44242361],"iteration":247,"passed_time":5.632897293,"remaining_time":8.494772531},
{"learn":[0.442376044],"iteration":248,"passed_time":5.658520142,"remaining_time":8.476417722},
{"learn":[0.4423347677],"iteration":249,"passed_time":5.680637324,"remaining_time":8.452788338},
{"learn":[0.4422751256],"iteration":250,"passed_time":5.705354201,"remaining_time":8.43301358},
{"learn":[0.4422042163],"iteration":251,"passed_time":5.728177834,"remaining_time":8.410419836},
{"learn":[0.4421421679],"iteration":252,"passed_time":5.751636288,"remaining_time":8.38875016},
{"learn":[0.4420885687],"iteration":253,"passed_time":5.775345035,"remaining_time":8.367429027},
{"learn":[0.4420255224],"iteration":254,"passed_time":5.798731399,"remaining_time":8.345625189},
{"learn":[0.4419709864],"iteration":255,"passed_time":5.821188989,"remaining_time":8.322481133},
{"learn":[0.4419129381],"iteration":256,"passed_time":5.849929273,"remaining_time":8.308265309},
{"learn":[0.4418525663],"iteration":257,"passed_time":5.873616306,"remaining_time":8.286807502},
{"learn":[0.4417892085],"iteration":258,"passed_time":5.898023275,"remaining_time":8.266341502},
{"learn":[0.4417244323],"iteration":259,"passed_time":5.921873818,"remaining_time":8.245070469},
{"learn":[0.441666333],"iteration":260,"passed_time":5.945699223,"remaining_time":8.223744902},
{"learn":[0.4416120182],"iteration":261,"passed_time":5.969327164,"remaining_time":8.202128928},
{"learn":[0.441566734],"iteration":262,"passed_time":5.990906761,"remaining_time":8.177701624},
{"learn":[0.4415192756],"iteration":263,"passed_time":6.014162821,"remaining_time":8.15556928},
{"learn":[0.4414724552],"iteration":264,"passed_time":6.037619371,"remaining_time":8.133698549},
{"learn":[0.4414169217],"iteration":265,"passed_time":6.062050253,"remaining_time":8.113119887},
{"learn":[0.4413701125],"iteration":266,"passed_time":6.084301766,"remaining_time":8.089614707},
{"learn":[0.441318015],"iteration":267,"passed_time":6.110479678,"remaining_time":8.071305246},
{"learn":[0.4412631799],"iteration":268,"passed_time":6.131917,"remaining_time":8.046716361},
{"learn":[0.4412089534],"iteration":269,"passed_time":6.156506367,"remaining_time":8.026260152},
{"learn":[0.441164634],"iteration":270,"passed_time":6.177630514,"remaining_time":8.001285278},
{"learn":[0.4411232065],"iteration":271,"passed_time":6.198944031,"remaining_time":7.976582393},
{"learn":[0.4410754465],"iteration":272,"passed_time":6.219735394,"remaining_time":7.951236822},
{"learn":[0.4410262679],"iteration":273,"passed_time":6.244476094,"remaining_time":7.930940441},
{"learn":[0.4409738164],"iteration":274,"passed_time":6.267527057,"remaining_time":7.908479595},
{"learn":[0.440922943],"iteration":275,"passed_time":6.289404907,"remaining_time":7.884543833},
{"learn":[0.4408639052],"iteration":276,"passed_time":6.31569093,"remaining_time":7.866113252},
{"learn":[0.440815582],"iteration":277,"passed_time":6.340606203,"remaining_time":7.845929978},
{"learn":[0.4407644492],"iteration":278,"passed_time":6.364574161,"remaining_time":7.824548163},
{"learn":[0.440723716],"iteration":279,"passed_time":6.38552631,"remaining_time":7.799464279},
{"learn":[0.4406543846],"iteration":280,"passed_time":6.409704057,"remaining_time":7.77832414},
{"learn":[0.4406037812],"iteration":281,"passed_time":6.43329763,"remaining_time":7.756458136},
{"learn":[0.4405526563],"iteration":282,"passed_time":6.45795247,"remaining_time":7.735851192},
{"learn":[0.4405066869],"iteration":283,"passed_time":6.480349453,"remaining_time":7.712528575},
{"learn":[0.4404578375],"iteration":284,"passed_time":6.503947416,"remaining_time":7.690632559},
{"learn":[0.4404088343],"iteration":285,"passed_time":6.527345799,"remaining_time":7.668490169},
{"learn":[0.4403686411],"iteration":286,"passed_time":6.548770241,"remaining_time":7.644034951},
{"learn":[0.4403293741],"iteration":287,"passed_time":6.574529145,"remaining_time":7.62462755},
{"learn":[0.4402859952],"iteration":288,"passed_time":6.597078633,"remaining_time":7.601478148},
{"learn":[0.440232145],"iteration":289,"passed_time":6.618575653,"remaining_time":7.577127989},
{"learn":[0.4401856209],"iteration":290,"passed_time":6.642195001,"remaining_time":7.555211496},
{"learn":[0.4401339228],"iteration":291,"passed_time":6.665681008,"remaining_time":7.533132645},
{"learn":[0.4400966263],"iteration":292,"passed_time":6.686557336,"remaining_time":7.508113869},
{"learn":[0.4400514265],"iteration":293,"passed_time":6.709634299,"remaining_time":7.485578401},
{"learn":[0.440005357],"iteration":294,"passed_time":6.731971817,"remaining_time":7.462219607},
{"learn":[0.4399605829],"iteration":295,"passed_time":6.753257832,"remaining_time":7.43770964},
{"learn":[0.4399175509],"iteration":296,"passed_time":6.773698722,"remaining_time":7.412296581},
{"learn":[0.4398673884],"iteration":297,"passed_time":6.794733667,"remaining_time":7.387562779},
{"learn":[0.4398225262],"iteration":298,"passed_time":6.82092902,"remaining_time":7.368428339},
{"learn":[0.4397815771],"iteration":299,"passed_time":6.841488677,"remaining_time":7.343197846},
{"learn":[0.4397365642],"iteration":300,"passed_time":6.863415381,"remaining_time":7.319456271},
{"learn":[0.4396957387],"iteration":301,"passed_time":6.885536779,"remaining_time":7.295933011},
{"learn":[0.4396486939],"iteration":302,"passed_time":6.907666487,"remaining_time":7.272427754},
{"learn":[0.4396116302],"iteration":303,"passed_time":6.929757465,"remaining_time":7.248891032},
{"learn":[0.4395542117],"iteration":304,"passed_time":6.955848825,"remaining_time":7.229521566},
{"learn":[0.4395119998],"iteration":305,"passed_time":6.980088708,"remaining_time":7.208196182},
{"learn":[0.4394583876],"iteration":306,"passed_time":7.004806209,"remaining_time":7.187341876},
{"learn":[0.4394158675],"iteration":307,"passed_time":7.027638399,"remaining_time":7.164540445},
{"learn":[0.4393657573],"iteration":308,"passed_time":7.049947271,"remaining_time":7.141208724},
{"learn":[0.4393099738],"iteration":309,"passed_time":7.075923534,"remaining_time":7.121574653},
{"learn":[0.4392788205],"iteration":310,"passed_time":7.096460442,"remaining_time":7.096460442},
{"learn":[0.439239911],"iteration":311,"passed_time":7.118650175,"remaining_time":7.073017802},
{"learn":[0.4392081666],"iteration":312,"passed_time":7.139011909,"remaining_time":7.04777853},
{"learn":[0.4391689362],"iteration":313,"passed_time":7.159146247,"remaining_time":7.022347274},
{"learn":[0.4391307062],"iteration":314,"passed_time":7.181843634,"remaining_time":6.999447605},
{"learn":[0.439074662],"iteration":315,"passed_time":7.208268354,"remaining_time":6.980158596},
{"learn":[0.4390384625],"iteration":316,"passed_time":7.230488402,"remaining_time":6.956779062},
{"learn":[0.4389944397],"iteration":317,"passed_time":7.252664636,"remaining_time":6.933364935},
{"learn":[0.4389479906],"iteration":318,"passed_time":7.275576063,"remaining_time":6.910656887},
{"learn":[0.4389084164],"iteration":319,"passed_time":7.299515926,"remaining_time":6.888918155},
{"learn":[0.4388756492],"iteration":320,"passed_time":7.322381477,"remaining_time":6.866158332},
{"learn":[0.4388327582],"iteration":321,"passed_time":7.342925169,"remaining_time":6.841234629},
{"learn":[0.4387958394],"iteration":322,"passed_time":7.365358001,"remaining_time":6.818086818},
{"learn":[0.4387423871],"iteration":323,"passed_time":7.389641255,"remaining_time":6.796645352},
{"learn":[0.4387090223],"iteration":324,"passed_time":7.412031863,"remaining_time":6.77345681},
{"learn":[0.4386665242],"iteration":325,"passed_time":7.43412532,"remaining_time":6.750003358},
{"learn":[0.43862565],"iteration":326,"passed_time":7.456039659,"remaining_time":6.726396635},
{"learn":[0.4385848819],"iteration":327,"passed_time":7.481434427,"remaining_time":6.705919883},
{"learn":[0.4385409071],"iteration":328,"passed_time":7.503748521,"remaining_time":6.682669656},
{"learn":[0.4384886249],"iteration":329,"passed_time":7.526402016,"remaining_time":6.65972542},
{"learn":[0.4384384466],"iteration":330,"passed_time":7.550203307,"remaining_time":6.637792032},
{"learn":[0.4384068789],"iteration":331,"passed_time":7.570552341,"remaining_time":6.612831864},
{"learn":[0.4383601851],"iteration":332,"passed_time":7.59399828,"remaining_time":6.590587096},
{"learn":[0.4383265724],"iteration":333,"passed_time":7.615547742,"remaining_time":6.566699849},
{"learn":[0.4382781382],"iteration":334,"passed_time":7.638035526,"remaining_time":6.543630436},
{"learn":[0.4382353493],"iteration":335,"passed_time":7.663907472,"remaining_time":6.52344505},
{"learn":[0.4381968213],"iteration":336,"passed_time":7.685827128,"remaining_time":6.499883476},
{"learn":[0.4381553406],"iteration":337,"passed_time":7.707054724,"remaining_time":6.475750123},
{"learn":[0.4381127804],"iteration":338,"passed_time":7.732014603,"remaining_time":6.454749654},
{"learn":[0.4380900217],"iteration":339,"passed_time":7.753991932,"remaining_time":6.431252132},
{"learn":[0.4380617219],"iteration":340,"passed_time":7.776705118,"remaining_time":6.408369906},
{"learn":[0.4380288544],"iteration":341,"passed_time":7.798274157,"remaining_time":6.384551942},
{"learn":[0.4379931463],"iteration":342,"passed_time":7.823484843,"remaining_time":6.363709245},
{"learn":[0.4379654033],"iteration":343,"passed_time":7.843025686,"remaining_time":6.33825913},
{"learn":[0.4379164517],"iteration":344,"passed_time":7.866080779,"remaining_time":6.315664857},
{"learn":[0.4378755048],"iteration":345,"passed_time":7.887937468,"remaining_time":6.292111969},
{"learn":[0.4378392715],"iteration":346,"passed_time":7.911596467,"remaining_time":6.2699972},
{"learn":[0.4378000459],"iteration":347,"passed_time":7.934724639,"remaining_time":6.247455606},
{"learn":[0.4377662274],"iteration":348,"passed_time":7.957106496,"remaining_time":6.224326858},
{"learn":[0.4377284831],"iteration":349,"passed_time":7.979052264,"remaining_time":6.200863474},
{"learn":[0.4377040045],"iteration":350,"passed_time":7.999322349,"remaining_time":6.176114976},
{"learn":[0.4376674193],"iteration":351,"passed_time":8.022133043,"remaining_time":6.153340687},
{"learn":[0.4376321526],"iteration":352,"passed_time":8.043822201,"remaining_time":6.129711536},
{"learn":[0.4375994882],"iteration":353,"passed_time":8.064578074,"remaining_time":6.10538679},
{"learn":[0.4375653826],"iteration":354,"passed_time":8.086025911,"remaining_time":6.081602586},
{"learn":[0.4375212726],"iteration":355,"passed_time":8.110683397,"remaining_time":6.060229729},
{"learn":[0.4374863125],"iteration":356,"passed_time":8.132964043,"remaining_time":6.03707415},
{"learn":[0.4374372229],"iteration":357,"passed_time":8.154188773,"remaining_time":6.013144794},
{"learn":[0.4373945706],"iteration":358,"passed_time":8.180442624,"remaining_time":5.992914791},
{"learn":[0.4373463912],"iteration":359,"passed_time":8.202320861,"remaining_time":5.969466849},
{"learn":[0.4373149307],"iteration":360,"passed_time":8.223807434,"remaining_time":5.945744433},
{"learn":[0.4372709577],"iteration":361,"passed_time":8.248804302,"remaining_time":5.924555576},
{"learn":[0.4372378468],"iteration":362,"passed_time":8.274753401,"remaining_time":5.904025154},
{"learn":[0.4372006149],"iteration":363,"passed_time":8.298024985,"remaining_time":5.88156716},
{"learn":[0.4371456788],"iteration":364,"passed_time":8.321682283,"remaining_time":5.859376293},
{"learn":[0.4371140951],"iteration":365,"passed_time":8.346069982,"remaining_time":5.837688294},
{"learn":[0.4371128048],"iteration":366,"passed_time":8.363837434,"remaining_time":5.811385683},
{"learn":[0.4370793844],"iteration":367,"passed_time":8.387542189,"remaining_time":5.789227489},
{"learn":[0.4370490934],"iteration":368,"passed_time":8.40849195,"remaining_time":5.765171987},
{"learn":[0.4369994016],"iteration":369,"passed_time":8.43225727,"remaining_time":5.743050898},
{"learn":[0.4369600743],"iteration":370,"passed_time":8.453906303,"remaining_time":5.71948917},
{"learn":[0.436914699],"iteration":371,"passed_time":8.476182223,"remaining_time":5.696359021},
{"learn":[0.4368821923],"iteration":372,"passed_time":8.501619626,"remaining_time":5.675343932},
{"learn":[0.4368595607],"iteration":373,"passed_time":8.521237342,"remaining_time":5.650446152},
{"learn":[0.4368248245],"iteration":374,"passed_time":8.543520058,"remaining_time":5.627331878},
{"learn":[0.4367790361],"iteration":375,"passed_time":8.566778466,"remaining_time":5.60486038},
{"learn":[0.4367670317],"iteration":376,"passed_time":8.586743587,"remaining_time":5.580244506},
{"learn":[0.4367323623],"iteration":377,"passed_time":8.609868922,"remaining_time":5.557693167},
{"learn":[0.4366973446],"iteration":378,"passed_time":8.631326029,"remaining_time":5.534069196},
{"learn":[0.4366589853],"iteration":379,"passed_time":8.653912031,"remaining_time":5.511175557},
{"learn":[0.4366252228],"iteration":380,"passed_time":8.677921162,"remaining_time":5.489183727},
{"learn":[0.4365909163],"iteration":381,"passed_time":8.701668426,"remaining_time":5.467016812},
{"learn":[0.4365884152],"iteration":382,"passed_time":8.719216368,"remaining_time":5.440973138},
{"learn":[0.436540807],"iteration":383,"passed_time":8.744923269,"remaining_time":5.420030568},
{"learn":[0.4365046587],"iteration":384,"passed_time":8.766316146,"remaining_time":5.396407602},
{"learn":[0.4364637865],"iteration":385,"passed_time":8.789818278,"remaining_time":5.374085787},
{"learn":[0.4364321566],"iteration":386,"passed_time":8.814785356,"remaining_time":5.352647438},
{"learn":[0.4363857725],"iteration":387,"passed_time":8.838984421,"remaining_time":5.330727718},
{"learn":[0.4363440089],"iteration":388,"passed_time":8.863446431,"remaining_time":5.308953775},
{"learn":[0.4363036008],"iteration":389,"passed_time":8.884500483,"remaining_time":5.285138749},
{"learn":[0.436268033],"iteration":390,"passed_time":8.908339603,"remaining_time":5.262983243},
{"learn":[0.436213613],"iteration":391,"passed_time":8.931285864,"remaining_time":5.240295277},
{"learn":[0.4361808114],"iteration":392,"passed_time":8.952680754,"remaining_time":5.216702017},
{"learn":[0.4361405238],"iteration":393,"passed_time":8.974298265,"remaining_time":5.193248742},
{"learn":[0.4360945542],"iteration":394,"passed_time":8.999439284,"remaining_time":5.171829665},
{"learn":[0.4360497636],"iteration":395,"passed_time":9.022707574,"remaining_time":5.149323009},
{"learn":[0.4360148613],"iteration":396,"passed_time":9.045687761,"remaining_time":5.126649235},
{"learn":[0.4359828597],"iteration":397,"passed_time":9.067231091,"remaining_time":5.103165237},
{"learn":[0.4359455188],"iteration":398,"passed_time":9.092709115,"remaining_time":5.081890057},
{"learn":[0.4359099541],"iteration":399,"passed_time":9.113406256,"remaining_time":5.057940472},
{"learn":[0.4358726854],"iteration":400,"passed_time":9.136929888,"remaining_time":5.035564851},
{"learn":[0.4358340074],"iteration":401,"passed_time":9.158597519,"remaining_time":5.012167796},
{"learn":[0.4357987671],"iteration":402,"passed_time":9.179478642,"remaining_time":4.988351917},
{"learn":[0.4357598789],"iteration":403,"passed_time":9.205423241,"remaining_time":4.967282838},
{"learn":[0.435722054],"iteration":404,"passed_time":9.228466653,"remaining_time":4.944635219},
{"learn":[0.4356858643],"iteration":405,"passed_time":9.253310282,"remaining_time":4.922943401},
{"learn":[0.4356481376],"iteration":406,"passed_time":9.277147039,"remaining_time":4.90070421},
{"learn":[0.4356166976],"iteration":407,"passed_time":9.298557171,"remaining_time":4.877184398},
{"learn":[0.4355691431],"iteration":408,"passed_time":9.324880764,"remaining_time":4.856233748},
{"learn":[0.4355501613],"iteration":409,"passed_time":9.346432543,"remaining_time":4.83278951},
{"learn":[0.4355201525],"iteration":410,"passed_time":9.368391424,"remaining_time":4.80956348},
{"learn":[0.4354969903],"iteration":411,"passed_time":9.389777995,"remaining_time":4.786051891},
{"learn":[0.4354711658],"iteration":412,"passed_time":9.41024848,"remaining_time":4.762087003},
{"learn":[0.4354282132],"iteration":413,"passed_time":9.435281694,"remaining_time":4.740431383},
{"learn":[0.4353896717],"iteration":414,"passed_time":9.458954084,"remaining_time":4.718080712},
{"learn":[0.4353460177],"iteration":415,"passed_time":9.482374673,"remaining_time":4.695598997},
{"learn":[0.435311242],"iteration":416,"passed_time":9.502190238,"remaining_time":4.671340525},
{"learn":[0.4352751682],"iteration":417,"passed_time":9.523917029,"remaining_time":4.648036062},
{"learn":[0.435243642],"iteration":418,"passed_time":9.545625026,"remaining_time":4.624730025},
{"learn":[0.4352015585],"iteration":419,"passed_time":9.568909989,"remaining_time":4.602190042},
{"learn":[0.4351639406],"iteration":420,"passed_time":9.592506379,"remaining_time":4.579795207},
{"learn":[0.4351134021],"iteration":421,"passed_time":9.615273668,"remaining_time":4.557001739},
{"learn":[0.4350808773],"iteration":422,"passed_time":9.636906571,"remaining_time":4.533674722},
{"learn":[0.435042419],"iteration":423,"passed_time":9.658096839,"remaining_time":4.510148996},
{"learn":[0.4350115404],"iteration":424,"passed_time":9.680813711,"remaining_time":4.487341885},
{"learn":[0.434975419],"iteration":425,"passed_time":9.706246138,"remaining_time":4.465784608},
{"learn":[0.4349297107],"iteration":426,"passed_time":9.72898516,"remaining_time":4.442979171},
{"learn":[0.4349010248],"iteration":427,"passed_time":9.749989126,"remaining_time":4.419387595},
{"learn":[0.4348644549],"iteration":428,"passed_time":9.771733113,"remaining_time":4.396141004},
{"learn":[0.4348284915],"iteration":429,"passed_time":9.793844052,"remaining_time":4.373065251},
{"learn":[0.4347901323],"iteration":430,"passed_time":9.820468143,"remaining_time":4.351994003},
{"learn":[0.4347578802],"iteration":431,"passed_time":9.846926911,"remaining_time":4.330824336},
{"learn":[0.4347135395],"iteration":432,"passed_time":9.871785334,"remaining_time":4.308931705},
{"learn":[0.4346863861],"iteration":433,"passed_time":9.893616376,"remaining_time":4.285714006},
{"learn":[0.4346524868],"iteration":434,"passed_time":9.914938919,"remaining_time":4.262284087},
{"learn":[0.4346174505],"iteration":435,"passed_time":9.939599156,"remaining_time":4.240287713},
{"learn":[0.434584743],"iteration":436,"passed_time":9.964822146,"remaining_time":4.218517384},
{"learn":[0.4345417936],"iteration":437,"passed_time":9.988564277,"remaining_time":4.196109194},
{"learn":[0.4345390209],"iteration":438,"passed_time":10.00543915,"remaining_time":4.170832264},
{"learn":[0.4344923988],"iteration":439,"passed_time":10.02793052,"remaining_time":4.147916716},
{"learn":[0.4344591745],"iteration":440,"passed_time":10.04797533,"remaining_time":4.123998944},
{"learn":[0.4344300755],"iteration":441,"passed_time":10.07051694,"remaining_time":4.101115498},
{"learn":[0.4343946631],"iteration":442,"passed_time":10.09150199,"remaining_time":4.077604642},
{"learn":[0.4343497973],"iteration":443,"passed_time":10.11464921,"remaining_time":4.054971982},
{"learn":[0.4343230574],"iteration":444,"passed_time":10.13749455,"remaining_time":4.032216932},
{"learn":[0.4342914111],"iteration":445,"passed_time":10.15892638,"remaining_time":4.008903682},
{"learn":[0.4342756073],"iteration":446,"passed_time":10.17771555,"remaining_time":3.984564252},
{"learn":[0.4342282794],"iteration":447,"passed_time":10.20378824,"remaining_time":3.963078468},
{"learn":[0.4341971333],"iteration":448,"passed_time":10.22399936,"remaining_time":3.939313784},
{"learn":[0.4341623472],"iteration":449,"passed_time":10.24620579,"remaining_time":3.916327546},
{"learn":[0.4341273146],"iteration":450,"passed_time":10.27204259,"remaining_time":3.894721247},
{"learn":[0.4341002072],"iteration":451,"passed_time":10.29209957,"remaining_time":3.870922403},
{"learn":[0.4340650161],"iteration":452,"passed_time":10.31732211,"remaining_time":3.849067188},
{"learn":[0.4340201365],"iteration":453,"passed_time":10.34265554,"remaining_time":3.827238175},
{"learn":[0.4339718818],"iteration":454,"passed_time":10.36768444,"remaining_time":3.805281983},
{"learn":[0.4339384756],"iteration":455,"passed_time":10.39150257,"remaining_time":3.78287155},
{"learn":[0.4339232738],"iteration":456,"passed_time":10.41088318,"remaining_time":3.758852789},
{"learn":[0.4338933331],"iteration":457,"passed_time":10.43094856,"remaining_time":3.735099484},
{"learn":[0.4338685108],"iteration":458,"passed_time":10.45382749,"remaining_time":3.712361397},
{"learn":[0.4338457097],"iteration":459,"passed_time":10.47478305,"remaining_time":3.688945334},
{"learn":[0.4338110615],"iteration":460,"passed_time":10.49849024,"remaining_time":3.66650093},
{"learn":[0.4337836909],"iteration":461,"passed_time":10.51862905,"remaining_time":3.642815254},
{"learn":[0.4337470947],"iteration":462,"passed_time":10.53925948,"remaining_time":3.619313731},
{"learn":[0.433723155],"iteration":463,"passed_time":10.55923541,"remaining_time":3.595601713},
{"learn":[0.4336949319],"iteration":464,"passed_time":10.57812681,"remaining_time":3.571539589},
{"learn":[0.4336715927],"iteration":465,"passed_time":10.59969511,"remaining_time":3.548395789},
{"learn":[0.4336376382],"iteration":466,"passed_time":10.62361643,"remaining_time":3.526039714},
{"learn":[0.433636739],"iteration":467,"passed_time":10.64091926,"remaining_time":3.501499071},
{"learn":[0.4336021688],"iteration":468,"passed_time":10.66389311,"remaining_time":3.478839329},
{"learn":[0.4335639195],"iteration":469,"passed_time":10.68511898,"remaining_time":3.455612945},
{"learn":[0.4335411388],"iteration":470,"passed_time":10.70685074,"remaining_time":3.432557242},
{"learn":[0.4335169386],"iteration":471,"passed_time":10.72939911,"remaining_time":3.409766667},
{"learn":[0.433486781],"iteration":472,"passed_time":10.75055677,"remaining_time":3.386539025},
{"learn":[0.4334530126],"iteration":473,"passed_time":10.7718777,"remaining_time":3.363371095},
{"learn":[0.4334352595],"iteration":474,"passed_time":10.79321344,"remaining_time":3.340215527},
{"learn":[0.4334099499],"iteration":475,"passed_time":10.8162597,"remaining_time":3.31759226},
{"learn":[0.4333744099],"iteration":476,"passed_time":10.83798537,"remaining_time":3.294565783},
{"learn":[0.4333467317],"iteration":477,"passed_time":10.85933785,"remaining_time":3.271432324},
{"learn":[0.4333168379],"iteration":478,"passed_time":10.88226615,"remaining_time":3.248776741},
{"learn":[0.4332794459],"iteration":479,"passed_time":10.90454693,"remaining_time":3.225928467},
{"learn":[0.4332700973],"iteration":480,"passed_time":10.92415893,"remaining_time":3.202300226},
{"learn":[0.4332315424],"iteration":481,"passed_time":10.9462069,"remaining_time":3.179396194},
{"learn":[0.4331991415],"iteration":482,"passed_time":10.9693408,"remaining_time":3.156808221},
{"learn":[0.4331608505],"iteration":483,"passed_time":10.99055911,"remaining_time":3.133671812},
{"learn":[0.4331294894],"iteration":484,"passed_time":11.01072708,"remaining_time":3.11024662},
{"learn":[0.4330959635],"iteration":485,"passed_time":11.0336915,"remaining_time":3.087617375},
{"learn":[0.4330589288],"iteration":486,"passed_time":11.07322178,"remaining_time":3.069578934},
{"learn":[0.4330260782],"iteration":487,"passed_time":11.09486395,"remaining_time":3.046540512},
{"learn":[0.4329955695],"iteration":488,"passed_time":11.11869498,"remaining_time":3.024103134},
{"learn":[0.4329673992],"iteration":489,"passed_time":11.14078636,"remaining_time":3.001191428},
{"learn":[0.4329340732],"iteration":490,"passed_time":11.16382786,"remaining_time":2.978536557},
{"learn":[0.4328865803],"iteration":491,"passed_time":11.1858827,"remaining_time":2.955619413},
{"learn":[0.4328506936],"iteration":492,"passed_time":11.20883225,"remaining_time":2.93293988},
{"learn":[0.4328018639],"iteration":493,"passed_time":11.23396388,"remaining_time":2.91082465},
{"learn":[0.4327804767],"iteration":494,"passed_time":11.25474309,"remaining_time":2.887580551},
{"learn":[0.4327509463],"iteration":495,"passed_time":11.28008117,"remaining_time":2.865504491},
{"learn":[0.4327154737],"iteration":496,"passed_time":11.30392441,"remaining_time":2.84303934},
{"learn":[0.4326761678],"iteration":497,"passed_time":11.32560965,"remaining_time":2.820031317},
{"learn":[0.4326450232],"iteration":498,"passed_time":11.34876658,"remaining_time":2.79739136},
{"learn":[0.4326040223],"iteration":499,"passed_time":11.3709228,"remaining_time":2.774505164},
{"learn":[0.4325672557],"iteration":500,"passed_time":11.39569901,"remaining_time":2.752254652},
{"learn":[0.4325335711],"iteration":501,"passed_time":11.41916011,"remaining_time":2.729679706},
{"learn":[0.4325091823],"iteration":502,"passed_time":11.44120983,"remaining_time":2.706767335},
{"learn":[0.4324845392],"iteration":503,"passed_time":11.46268602,"remaining_time":2.683724108},
{"learn":[0.4324607101],"iteration":504,"passed_time":11.48296777,"remaining_time":2.660410354},
{"learn":[0.4324301734],"iteration":505,"passed_time":11.50346971,"remaining_time":2.637159065},
{"learn":[0.4324100676],"iteration":506,"passed_time":11.5260028,"remaining_time":2.614379333},
{"learn":[0.4323932935],"iteration":507,"passed_time":11.54540873,"remaining_time":2.590898809},
{"learn":[0.4323587916],"iteration":508,"passed_time":11.56729673,"remaining_time":2.567985324},
{"learn":[0.4323327347],"iteration":509,"passed_time":11.58730842,"remaining_time":2.544663809},
{"learn":[0.4323042005],"iteration":510,"passed_time":11.60997375,"remaining_time":2.521931676},
{"learn":[0.4323015709],"iteration":511,"passed_time":11.62900687,"remaining_time":2.498419445},
{"learn":[0.4322665052],"iteration":512,"passed_time":11.65333591,"remaining_time":2.476049931},
{"learn":[0.4322272394],"iteration":513,"passed_time":11.67446223,"remaining_time":2.452999845},
{"learn":[0.4321999603],"iteration":514,"passed_time":11.69712591,"remaining_time":2.430276645},
{"learn":[0.4321680152],"iteration":515,"passed_time":11.71825552,"remaining_time":2.407238538},
{"learn":[0.4321385867],"iteration":516,"passed_time":11.73830389,"remaining_time":2.383988218},
{"learn":[0.4321164216],"iteration":517,"passed_time":11.76010851,"remaining_time":2.361102867},
{"learn":[0.4320680965],"iteration":518,"passed_time":11.78393563,"remaining_time":2.338623064},
{"learn":[0.4320246743],"iteration":519,"passed_time":11.80692632,"remaining_time":2.315974009},
{"learn":[0.4320039224],"iteration":520,"passed_time":11.8300991,"remaining_time":2.293358943},
{"learn":[0.4319633712],"iteration":521,"passed_time":11.85336874,"remaining_time":2.270760294},
{"learn":[0.4319317171],"iteration":522,"passed_time":11.87735518,"remaining_time":2.248294766},
{"learn":[0.4318824462],"iteration":523,"passed_time":11.90184591,"remaining_time":2.225917747},
{"learn":[0.4318392953],"iteration":524,"passed_time":11.92647521,"remaining_time":2.203558276},
{"learn":[0.43182357],"iteration":525,"passed_time":11.95047322,"remaining_time":2.181074961},
{"learn":[0.4317807001],"iteration":526,"passed_time":11.97784639,"remaining_time":2.15919432},
{"learn":[0.431739226],"iteration":527,"passed_time":11.99988197,"remaining_time":2.136342624},
{"learn":[0.4317076966],"iteration":528,"passed_time":12.02013301,"remaining_time":2.113180284},
{"learn":[0.4316750964],"iteration":529,"passed_time":12.04381609,"remaining_time":2.09062468},
{"learn":[0.4316613185],"iteration":530,"passed_time":12.06394267,"remaining_time":2.067455335},
{"learn":[0.4316345134],"iteration":531,"passed_time":12.08411757,"remaining_time":2.044305604},
{"learn":[0.4315855566],"iteration":532,"passed_time":12.10963564,"remaining_time":2.022059235},
{"learn":[0.4315458858],"iteration":533,"passed_time":12.13287182,"remaining_time":1.99942457},
{"learn":[0.4315121106],"iteration":534,"passed_time":12.15780048,"remaining_time":1.977062882},
{"learn":[0.4314844074],"iteration":535,"passed_time":12.18115872,"remaining_time":1.954439645},
{"learn":[0.4314526585],"iteration":536,"passed_time":12.20623711,"remaining_time":1.932085948},
{"learn":[0.4314192674],"iteration":537,"passed_time":12.22853743,"remaining_time":1.909288372},
{"learn":[0.4313877701],"iteration":538,"passed_time":12.25058295,"remaining_time":1.886453405},
{"learn":[0.4313577385],"iteration":539,"passed_time":12.27349194,"remaining_time":1.86375248},
{"learn":[0.4313278016],"iteration":540,"passed_time":12.29773041,"remaining_time":1.84124984},
{"learn":[0.4312954439],"iteration":541,"passed_time":12.31953481,"remaining_time":1.818381522},
{"learn":[0.4312732471],"iteration":542,"passed_time":12.34043381,"remaining_time":1.795385398},
{"learn":[0.4312488088],"iteration":543,"passed_time":12.36220927,"remaining_time":1.772522653},
{"learn":[0.4312163515],"iteration":544,"passed_time":12.38479125,"remaining_time":1.749777846},
{"learn":[0.431178252],"iteration":545,"passed_time":12.4094086,"remaining_time":1.727316948},
{"learn":[0.4311559566],"iteration":546,"passed_time":12.42966836,"remaining_time":1.704250689},
{"learn":[0.4311285855],"iteration":547,"passed_time":12.4523616,"remaining_time":1.681523282},
{"learn":[0.4311061924],"iteration":548,"passed_time":12.47693414,"remaining_time":1.659045888},
{"learn":[0.4310797056],"iteration":549,"passed_time":12.50240008,"remaining_time":1.636677829},
{"learn":[0.4310417606],"iteration":550,"passed_time":12.52455047,"remaining_time":1.613871294},
{"learn":[0.4310193265],"iteration":551,"passed_time":12.54608111,"remaining_time":1.590988546},
{"learn":[0.4309765726],"iteration":552,"passed_time":12.56859841,"remaining_time":1.568233798},
{"learn":[0.4309644062],"iteration":553,"passed_time":12.58871524,"remaining_time":1.545185264},
{"learn":[0.430943602],"iteration":554,"passed_time":12.60985501,"remaining_time":1.522270785},
{"learn":[0.4309248351],"iteration":555,"passed_time":12.63139639,"remaining_time":1.499410363},
{"learn":[0.4309017501],"iteration":556,"passed_time":12.65351592,"remaining_time":1.476622145},
{"learn":[0.4308814558],"iteration":557,"passed_time":12.67271625,"remaining_time":1.453501505},
{"learn":[0.4308604248],"iteration":558,"passed_time":12.69364042,"remaining_time":1.430589171},
{"learn":[0.4308293048],"iteration":559,"passed_time":12.7157626,"remaining_time":1.407816573},
{"learn":[0.4308084011],"iteration":560,"passed_time":12.73666558,"remaining_time":1.384913726},
{"learn":[0.4307836912],"iteration":561,"passed_time":12.75732919,"remaining_time":1.361992441},
{"learn":[0.4307530988],"iteration":562,"passed_time":12.77897201,"remaining_time":1.339181791},
{"learn":[0.4307196508],"iteration":563,"passed_time":12.80295969,"remaining_time":1.316616422},
{"learn":[0.4306898413],"iteration":564,"passed_time":12.82690883,"remaining_time":1.29404213},
{"learn":[0.4306498467],"iteration":565,"passed_time":12.85052935,"remaining_time":1.271430465},
{"learn":[0.4306201815],"iteration":566,"passed_time":12.87208049,"remaining_time":1.248614509},
{"learn":[0.4305882195],"iteration":567,"passed_time":12.89316792,"remaining_time":1.225758922},
{"learn":[0.4305493233],"iteration":568,"passed_time":12.91748477,"remaining_time":1.203210357},
{"learn":[0.4305253175],"iteration":569,"passed_time":12.93859662,"remaining_time":1.1803632},
{"learn":[0.4304924926],"iteration":570,"passed_time":12.96057247,"remaining_time":1.157599293},
{"learn":[0.4304891187],"iteration":571,"passed_time":12.97898663,"remaining_time":1.134526803},
{"learn":[0.4304689106],"iteration":572,"passed_time":12.99999159,"remaining_time":1.111692126},
{"learn":[0.4304412308],"iteration":573,"passed_time":13.02427992,"remaining_time":1.089138391},
{"learn":[0.4304141014],"iteration":574,"passed_time":13.04570922,"remaining_time":1.066344927},
{"learn":[0.4303733316],"iteration":575,"passed_time":13.07047104,"remaining_time":1.04382234},
{"learn":[0.4303389787],"iteration":576,"passed_time":13.09221527,"remaining_time":1.02105665},
{"learn":[0.4303096283],"iteration":577,"passed_time":13.11354791,"remaining_time":0.9982631627},
{"learn":[0.4302850264],"iteration":578,"passed_time":13.13519098,"remaining_time":0.9754977759},
{"learn":[0.4302677641],"iteration":579,"passed_time":13.15543462,"remaining_time":0.9526349207},
{"learn":[0.430230628],"iteration":580,"passed_time":13.17789987,"remaining_time":0.9299378563},
{"learn":[0.4302003249],"iteration":581,"passed_time":13.20295935,"remaining_time":0.9074198867},
{"learn":[0.4301700671],"iteration":582,"passed_time":13.22434903,"remaining_time":0.884647705},
{"learn":[0.4301441708],"iteration":583,"passed_time":13.24658674,"remaining_time":0.8619354387},
{"learn":[0.4301362985],"iteration":584,"passed_time":13.26515798,"remaining_time":0.8389928982},
{"learn":[0.4300993908],"iteration":585,"passed_time":13.28750225,"remaining_time":0.8162970667},
{"learn":[0.4300661908],"iteration":586,"passed_time":13.30847809,"remaining_time":0.7935208401},
{"learn":[0.4300326621],"iteration":587,"passed_time":13.33078671,"remaining_time":0.7708278031},
{"learn":[0.430004176],"iteration":588,"passed_time":13.35201285,"remaining_time":0.7480754231},
{"learn":[0.4299647225],"iteration":589,"passed_time":13.37691803,"remaining_time":0.7255277574},
{"learn":[0.4299309359],"iteration":590,"passed_time":13.39810478,"remaining_time":0.7027770698},
{"learn":[0.4299010072],"iteration":591,"passed_time":13.42006985,"remaining_time":0.6800711074},
{"learn":[0.4298706119],"iteration":592,"passed_time":13.44257548,"remaining_time":0.657394079},
{"learn":[0.4298507554],"iteration":593,"passed_time":13.46330729,"remaining_time":0.6346340138},
{"learn":[0.4298137727],"iteration":594,"passed_time":13.48639382,"remaining_time":0.6119876186},
{"learn":[0.4297913763],"iteration":595,"passed_time":13.50914608,"remaining_time":0.5893251644},
{"learn":[0.4297627633],"iteration":596,"passed_time":13.53294527,"remaining_time":0.5667062508},
{"learn":[0.4297244989],"iteration":597,"passed_time":13.55707832,"remaining_time":0.5440967887},
{"learn":[0.4297191742],"iteration":598,"passed_time":13.57551445,"remaining_time":0.5212634932},
{"learn":[0.429689439],"iteration":599,"passed_time":13.59833882,"remaining_time":0.4986057566},
{"learn":[0.4296623616],"iteration":600,"passed_time":13.61873646,"remaining_time":0.4758626716},
{"learn":[0.4296363287],"iteration":601,"passed_time":13.64111959,"remaining_time":0.4531933417},
{"learn":[0.4296145157],"iteration":602,"passed_time":13.66465434,"remaining_time":0.4305612478},
{"learn":[0.4295839405],"iteration":603,"passed_time":13.68815,"remaining_time":0.4079249999},
{"learn":[0.4295603417],"iteration":604,"passed_time":13.7101616,"remaining_time":0.3852442103},
{"learn":[0.4295275523],"iteration":605,"passed_time":13.73305285,"remaining_time":0.3625888541},
{"learn":[0.4294932907],"iteration":606,"passed_time":13.75438459,"remaining_time":0.3398941827},
{"learn":[0.4294695388],"iteration":607,"passed_time":13.77696974,"remaining_time":0.3172328558},
{"learn":[0.4294411654],"iteration":608,"passed_time":13.79797984,"remaining_time":0.2945381575},
{"learn":[0.4294102314],"iteration":609,"passed_time":13.82043668,"remaining_time":0.271877443},
{"learn":[0.4293868026],"iteration":610,"passed_time":13.84103136,"remaining_time":0.2491838706},
{"learn":[0.4293548538],"iteration":611,"passed_time":13.86327799,"remaining_time":0.2265241502},
{"learn":[0.4293317389],"iteration":612,"passed_time":13.8842318,"remaining_time":0.2038467964},
{"learn":[0.4292992661],"iteration":613,"passed_time":13.90701649,"remaining_time":0.1811989119},
{"learn":[0.4292732388],"iteration":614,"passed_time":13.927792,"remaining_time":0.1585277139},
{"learn":[0.4292344651],"iteration":615,"passed_time":13.94897934,"remaining_time":0.1358666818},
{"learn":[0.4292088236],"iteration":616,"passed_time":13.97042655,"remaining_time":0.1132125328},
{"learn":[0.4291786275],"iteration":617,"passed_time":13.99173479,"remaining_time":0.09056139024},
{"learn":[0.4291549613],"iteration":618,"passed_time":14.01477255,"remaining_time":0.06792296874},
{"learn":[0.4291180691],"iteration":619,"passed_time":14.03682184,"remaining_time":0.04528007044},
{"learn":[0.4290899046],"iteration":620,"passed_time":14.06105961,"remaining_time":0.02264260807},
{"learn":[0.4290556128],"iteration":621,"passed_time":14.08293011,"remaining_time":0}
]}